<images>
	<image id="000000001" description="clock"/>
	<image id="000000002" description="clipboard"/>
	<image id="000000003" description="people and lightbulb"/>
	<image id="000000004" description="tiered people"/>
	<image id="000000005" description="microphone"/>
	<image id="000000006" description="people around table"/>
	<image id="000000007" description="headphones"/>
	<image id="000000008" description="teacher and students with board"/>
	<image id="000000009" description="scroll with swirls"/>
	<image id="000000010" description="cloud with lightening"/>
	<image id="000000011" description="person balancing"/>
	<image id="000000012" description="checkmark"/>
	<image id="000000013" description="bullet point"/>
	<image id="000000014" description="heart in circle"/>
	<image id="000000015" description="person in circle with node branches"/>
	<image id="000000016" description="infinity symbol"/>
	<image id="000000017" description="shield with checkmark"/>
	<image id="000000018" description="community example 1"/>
	<image id="000000019" description="community example 2"/>
	<image id="000000020" description="community example 3"/>
	<image id="000000021" description="goal setting table"/>
	<image id="000000022" description="activity selection table"/>
</images>