<textBlocks>
	<container id="formVBox">
		<textBlock>
			<text
			size="25.0"
			fontFamily="System"
			fontStyle="Bold"
			text="Team storytelling activity">
			</text>
		</textBlock>
		<textBlock>
			<text
			size="16.0"
			fontFamily="System"
			fontStyle="Regular"
			text="Invite core team members to share stories about their experiences with disaster mitigation, preparation, response and/or recovery">
			</text>
		</textBlock>
		<textBlock>
			<text
			size="16.0"
			fontFamily="System"
			fontStyle="Bold"
			text="Why do this: ">
			</text>
			<text
			size="16.0"
			fontFamily="System"
			fontStyle="Regular"
			text="&#xD;It will help you build team rapport, ">
			</text>
			<text
			size="16.0"
			fontFamily="System"
			fontStyle="Hyperlink"
			text="set goals"
			linkType="internalActivity"
			link="000002">
			</text>
			<text
			size="16.0"
			fontFamily="System"
			fontStyle="Regular"
			text=" for using ERB, and get ready to lead storytelling as part of ">
			</text>
			<text
			size="16.0"
			fontFamily="System"
			fontStyle="Hyperlink"
			text="community workshops "
			linkType="internalActivity"
			link="000010">
			</text>
			<text
			size="16.0"
			fontFamily="System"
			fontStyle="Regular"
			text=". Learn more about why ">
			</text>
			<text
			size="16.0"
			fontFamily="System"
			fontStyle="Hyperlink"
			text="ERB uses storytelling"
			linkType="internalResource"
			link="02">
			</text>
			<text
			size="16.0"
			fontFamily="System"
			fontStyle="Regular"
			text=" and ">
			</text>
			<text
			size="16.0"
			fontFamily="System"
			fontStyle="Hyperlink"
			text="storytelling best practices"
			linkType="internalResource"
			link="03">
			</text>
			<text
			size="16.0"
			fontFamily="System"
			fontStyle="Regular"
			text=".">
			</text>
		</textBlock>
		<textBlock>
			<text
			size="16.0"
			fontFamily="System"
			fontStyle="Bold"
			text="How to do this: ">
			</text>
			<text
			size="16.0"
			fontFamily="System"
			fontStyle="Regular"
			text="&#xD;During a team meeting, the activity lead gives everyone a copy of the ">
			</text>
			<text
			size="16.0"
			fontFamily="System"
			fontStyle="Hyperlink"
			text="Team Storytelling worksheet"
			linkType="externalDOC"
			link="Ch1_team_storytelling_activity_worksheet.docx">
			</text>
			<text
			size="16.0"
			fontFamily="System"
			fontStyle="Regular"
			text=", which contains instructions and a story prompt. The group then takes turns sharing and listening to stories in response to the prompt. Afterwards, the activity lead can input highlights into the ">
			</text>
			<text
			size="16.0"
			fontFamily="System"
			fontStyle="Hyperlink"
			text="Team Storytelling worksheet"
			linkType="externalDOC"
			link="Ch1_team_storytelling_activity_worksheet.docx">
			</text>
			<text
			size="16.0"
			fontFamily="System"
			fontStyle="Regular"
			text=". Pro tip: make sure storytellers are okay with what you input and leave out details that might compromise their anonymity.">
			</text>
		</textBlock>
	</container>
	<container id="topPanelVBox">
		<textBlock>
			<text
			size="16.0"
			fontFamily="System"
			fontStyle="Bold"
			text="Things you'll need:">
			</text>
			<text
			size="16.0"
			fontFamily="System"
			fontStyle="Underlined"
			text="&#xD;Time:">
			</text>
			<text
			size="16.0"
			fontFamily="System"
			fontStyle="Regular"
			text=" 1/2 hour prep; 1 hour meeting; 15 min. Record results">
			</text>
			<text
			size="16.0"
			fontFamily="System"
			fontStyle="Underlined"
			text="&#xD;Materials:">
			</text>
			<text
			size="16.0"
			fontFamily="System"
			fontStyle="Regular"
			text="&#xD;&#x9;- Team storytelling worksheet [">
			</text>
			<text
			size="16.0"
			fontFamily="System"
			fontStyle="Hyperlink"
			text="link"
			linkType="externalDOC"
			link="Ch1_team_storytelling_activity_worksheet.docx">
			</text>
			<text
			size="16.0"
			fontFamily="System"
			fontStyle="Regular"
			text="]">
			</text>
		</textBlock>
	</container>
		<container id="bottomPanelVBox">
		<textBlock>
			<text
			size="16.0"
			fontFamily="System"
			fontStyle="Bold"
			text="Activity output:">
			</text>
			<text
			size="16.0"
			fontFamily="System"
			fontStyle="Regular"
			text="&#xD;- Team storytelling results">
			</text>
		</textBlock>
	</container>
</textBlocks>
